graphene_health/__init__.py
graphene_health/cli.py
graphene_health/config-defaults.yaml
graphene_health/config.py
graphene_health/test_api.py
graphene_health/utils.py
graphene_health/views.py
graphene_healthchecker-0.1.10.dist-info/LICENSE.txt
graphene_healthchecker-0.1.10.dist-info/METADATA
graphene_healthchecker-0.1.10.dist-info/WHEEL
graphene_healthchecker-0.1.10.dist-info/entry_points.txt
graphene_healthchecker-0.1.10.dist-info/top_level.txt
graphene_healthchecker-0.1.10.dist-info/RECORD
