Metadata-Version: 2.1
Name: graphene-healthchecker
Version: 0.1.10
Summary: Python library for RPC-healthchecking for graphene blockchains
Home-page: https://github.com/chainsquad/graphene-healthchecker
Author: ChainSquad GmbH
Author-email: Fabian@chainsquad.com
Maintainer: Fabian Schuh
Maintainer-email: Fabian@chainsquad.com
License: UNKNOWN
Download-URL: https://github.com/chainsquad/graphene-healthchecker/tarball/0.1.10
Keywords: graphene,blockchain,health,api,rpc
Platform: UNKNOWN
Classifier: License :: OSI Approved :: MIT License
Classifier: Operating System :: OS Independent
Classifier: Programming Language :: Python :: 3
Classifier: Development Status :: 3 - Alpha
Classifier: Intended Audience :: Developers
Classifier: Intended Audience :: Financial and Insurance Industry
Classifier: Topic :: Office/Business :: Financial
Requires-Dist: pyyaml
Requires-Dist: flask
Requires-Dist: flask-testing
Requires-Dist: requests
Requires-Dist: prometheus-client
Requires-Dist: uwsgi
Requires-Dist: werkzeug (==0.16.0)
Requires-Dist: py-healthcheck
